Windows.py
download.py
hyyToolbox.py
other.py
hyyToolbox-1.0.4.dist-info/LICENSE.txt
hyyToolbox-1.0.4.dist-info/METADATA
hyyToolbox-1.0.4.dist-info/WHEEL
hyyToolbox-1.0.4.dist-info/top_level.txt
hyyToolbox-1.0.4.dist-info/RECORD
