Metadata-Version: 2.1
Name: hyyToolbox
Version: 1.0.4
Summary: hyyToolbox have Administrator Privileges and Create a Shortcut...
Author: huang yi yi
Author-email: 363766687@qq.com
License-File: LICENSE.txt
